logging_assignment3/__init__.py
logging_assignment3/logger_assignment3.py
assignment3_us_advpython-0.1.0.dist-info/METADATA
assignment3_us_advpython-0.1.0.dist-info/WHEEL
assignment3_us_advpython-0.1.0.dist-info/top_level.txt
assignment3_us_advpython-0.1.0.dist-info/RECORD
