Metadata-Version: 2.1
Name: assignment3-us-advpython
Version: 0.1.0
Summary: Assignment 3
Home-page: https://gitlab.com/UMaksat/assignment3
Author: MaxatUal
Author-email: walikhan19112002@gmail.com
